marshmallow_patch/__init__.py
marshmallow_patch/config.py
marshmallow_patch/marshmallow/__init__.py
marshmallow_patch/marshmallow/fields.py
pedroasad_marshmallow_patch-0.2.0.dist-info/LICENSE.txt
pedroasad_marshmallow_patch-0.2.0.dist-info/WHEEL
pedroasad_marshmallow_patch-0.2.0.dist-info/METADATA
pedroasad_marshmallow_patch-0.2.0.dist-info/RECORD
