Metadata-Version: 2.1
Name: pedroasad-marshmallow-patch
Version: 0.2.0
Summary: A set of patches to the excellect marshmallow library
Home-page: https://psa-exe.gitlab.io/python-marshmallow-patch
License: MIT
Author: Pedro Asad
Author-email: pasad@lcg.ufrj.br
Requires-Python: >=3.6,<4.0
Classifier: License :: OSI Approved :: MIT License
Classifier: Programming Language :: Python :: 3
Classifier: Programming Language :: Python :: 3.6
Classifier: Programming Language :: Python :: 3.7
Provides-Extra: all
Provides-Extra: numpy
Provides-Extra: pint
Requires-Dist: marshmallow (>=2.19,<3.0)
Requires-Dist: marshmallow_annotations (>=2.4,<3.0)
Requires-Dist: numpy (>=1.16,<2.0); extra == "all" or extra == "numpy"
Requires-Dist: pint (>=0.9.0,<0.10.0); extra == "all" or extra == "pint"
Project-URL: Documentation, https://psa-exe.gitlab.io/python-marshmallow-patch
Project-URL: Repository, https://gitlab.com/psa-exe//python-marshmallow-patch
